supergpt/__init__.py
supergpt-1.0.1.dist-info/METADATA
supergpt-1.0.1.dist-info/WHEEL
supergpt-1.0.1.dist-info/top_level.txt
supergpt-1.0.1.dist-info/RECORD
