Metadata-Version: 2.4
Name: supergpt
Version: 1.0.1
Summary: A Artificial Intelligence chatbot
Author-email: Thái Lâm <thailam160317@outlook.com>
License: MIT
Requires-Python: >=3.9
Requires-Dist: google-genai>=1.24.0
Requires-Dist: requests>=2.28.1
Requires-Dist: tenacity>=8.2.3
